data_collect/__init__.py
data_collect/client.py
data_collect/constants.py
data_collect/correlation_id.py
data_collect/logger.py
data_collect/queue.py
data_collect/setup.py
data_collect/thread.py
data_collect/utils.py
data_collect/data_types/__init__.py
data_collect/data_types/blob.py
data_collect/data_types/image.py
data_collect/data_types/text.py
data_collect-0.8.9.dist-info/METADATA
data_collect-0.8.9.dist-info/WHEEL
data_collect-0.8.9.dist-info/top_level.txt
data_collect-0.8.9.dist-info/RECORD
