Metadata-Version: 2.1
Name: data-collect
Version: 0.8.9
Summary: project descriptions here
Home-page: https://github.com/FlyTOmeLight
Author: zhoubohan
Author-email: zhoubohan.pro@gmail.com
License: MIT
Platform: UNKNOWN
Classifier: Programming Language :: Python
Classifier: Programming Language :: Python :: 3
Classifier: Programming Language :: Python :: 3.7
Classifier: Programming Language :: Python :: 3.8
Classifier: Programming Language :: Python :: 3.9
Requires-Python: >=3.7
Requires-Dist: pybind11 (>=2.4.2)
Requires-Dist: Pillow (>=9.2.0)
Requires-Dist: numpy (>=1.21.6)
Requires-Dist: pydantic (>=1.10.4)
Requires-Dist: spdlog (>=2.0.4)
